[
  {
    "ContainingType": "PhoenicianCapital.Controllers.AgentController",
    "Method": "RunAgent",
    "RelativePath": "api/Agent/run",
    "HttpMethod": "POST",
    "IsController": true,
    "Order": 0,
    "Parameters": [
      {
        "Name": "request",
        "Type": "PhoenicianCapital.DTO.Agent.AgentRunRequest",
        "IsRequired": true
      }
    ],
    "ReturnTypes": []
  },
  {
    "ContainingType": "PhoenicianCapital.Controllers.AuthController",
    "Method": "Login",
    "RelativePath": "api/Auth/login",
    "HttpMethod": "POST",
    "IsController": true,
    "Order": 0,
    "Parameters": [
      {
        "Name": "request",
        "Type": "PhoenicianCapital.DTO.Auth.LoginRequest",
        "IsRequired": true
      }
    ],
    "ReturnTypes": [
      {
        "Type": "PhoenicianCapital.DTO.Common.ApiResponse\u00601[[System.String, System.Private.CoreLib, Version=9.0.0.0, Culture=neutral, PublicKeyToken=7cec85d7bea7798e]]",
        "MediaTypes": [
          "text/plain",
          "application/json",
          "text/json"
        ],
        "StatusCode": 200
      }
    ]
  },
  {
    "ContainingType": "PhoenicianCapital.Controllers.AuthController",
    "Method": "Me",
    "RelativePath": "api/Auth/me",
    "HttpMethod": "GET",
    "IsController": true,
    "Order": 0,
    "Parameters": [],
    "ReturnTypes": [
      {
        "Type": "PhoenicianCapital.DTO.Common.ApiResponse\u00601[[System.Object, System.Private.CoreLib, Version=9.0.0.0, Culture=neutral, PublicKeyToken=7cec85d7bea7798e]]",
        "MediaTypes": [
          "text/plain",
          "application/json",
          "text/json"
        ],
        "StatusCode": 200
      }
    ]
  },
  {
    "ContainingType": "PhoenicianCapital.Controllers.AuthController",
    "Method": "Register",
    "RelativePath": "api/Auth/register",
    "HttpMethod": "POST",
    "IsController": true,
    "Order": 0,
    "Parameters": [
      {
        "Name": "request",
        "Type": "PhoenicianCapital.DTO.Auth.SignupRequest",
        "IsRequired": true
      }
    ],
    "ReturnTypes": [
      {
        "Type": "PhoenicianCapital.DTO.Common.ApiResponse\u00601[[System.String, System.Private.CoreLib, Version=9.0.0.0, Culture=neutral, PublicKeyToken=7cec85d7bea7798e]]",
        "MediaTypes": [
          "text/plain",
          "application/json",
          "text/json"
        ],
        "StatusCode": 200
      }
    ]
  }
]